Metadata-Version: 1.0
Name: coop-agenda
Version: 0.1.3
Summary: Companion app for django-coop, a fork of swingtime
Home-page: https://github.com/quinode/coop_agenda/
Author: Dominique Guardiola
Author-email: dguardiola@quinode.fr
License: BSD
Download-URL: https://github.com/quinode/coop_agenda/tarball/master
Platform: UNKNOWN
Classifier: Development Status :: 4 - Beta
Classifier: Environment :: Web Environment
Classifier: Intended Audience :: Developers
Classifier: License :: OSI Approved :: BSD License
Classifier: Operating System :: OS Independent
Classifier: Programming Language :: Python
Classifier: Framework :: Django
Classifier: Natural Language :: English
Classifier: Natural Language :: French
Classifier: Topic :: Internet :: WWW/HTTP :: Dynamic Content
Classifier: Topic :: Internet :: WWW/HTTP :: WSGI :: Application
